setup.py
dummy_txredis/__init__.py
dummy_txredis/protocol.py
dummy_txredis.egg-info/PKG-INFO
dummy_txredis.egg-info/SOURCES.txt
dummy_txredis.egg-info/dependency_links.txt
dummy_txredis.egg-info/not-zip-safe
dummy_txredis.egg-info/requires.txt
dummy_txredis.egg-info/top_level.txt