Metadata-Version: 1.0
Name: dummy-txredis
Version: 0.5
Summary: Dummy txRedis
Home-page: https://github.com/williamsjj/dummy-txredis
Author: Jason Williams
Author-email: jasonjwwilliams@gmail.com
License: BSD
Download-URL: https://github.com/williamsjj/dummy-txredis/zipball/v0.5
Platform: UNKNOWN
